{"stat": "ok", "comments": {"comment": [{"permalink": "http://www.flickr.com/photos/field_museum_library/3349699278/#comment72157622529314966", "realname": "Joana Garrido", "path_alias": "onomatoh", "author": "79992696@N00", "iconserver": "3116", "datecreate": "1254844967", "_content": "Oh my!", "authorname": "onomatoh", "id": "35278557-3349699278-72157622529314966", "iconfarm": 4}, {"permalink": "http://www.flickr.com/photos/field_museum_library/3349699278/#comment72157622558047442", "realname": "Jennifer  Holcombe", "path_alias": "jenphotography", "author": "53055958@N00", "iconserver": "142", "datecreate": "1255219996", "_content": "Hi, I'm an admin for a group called <a href=\"http://www.flickr.com/groups/856962@N24/\">((( transcend d\u00e9passez supere \u8d85\u8d8a\u3057\u306a\u3055\u3044 )))</a>, and we'd love to have this added to the group!", "authorname": "Jen's Photography", "id": "35278557-3349699278-72157622558047442", "iconfarm": 1}, {"permalink": "http://www.flickr.com/photos/field_museum_library/3349699278/#comment72157625809732154", "realname": "John Donnellan", "path_alias": "photojondon", "author": "52413098@N00", "iconserver": "7423", "datecreate": "1294866698", "_content": "where can I get one of those?", "authorname": "John Donnellan", "id": "35278557-3349699278-72157625809732154", "iconfarm": 8}, {"permalink": "http://www.flickr.com/photos/field_museum_library/3349699278/#comment72157630964717860", "realname": "", "path_alias": "baggins", "author": "30342831@N00", "iconserver": "1221", "datecreate": "1344398403", "_content": "where is it now?", "authorname": "baggins@well.com", "id": "35278557-3349699278-72157630964717860", "iconfarm": 2}], "photo_id": "3349699278"}, "flarchive:created": 1389364775}