{"stat": "ok", "flarchive:created": 1387761380, "sizes": {"canblog": 0, "size": [{"source": "http://farm4.staticflickr.com/3055/2958169439_3ddb956bfc_s.jpg", "url": "http://www.flickr.com/photos/biblarte/2958169439/sizes/sq/", "media": "photo", "height": 75, "width": 75, "label": "Square"}, {"source": "http://farm4.staticflickr.com/3055/2958169439_3ddb956bfc_q.jpg", "url": "http://www.flickr.com/photos/biblarte/2958169439/sizes/q/", "media": "photo", "height": "150", "width": "150", "label": "Large Square"}, {"source": "http://farm4.staticflickr.com/3055/2958169439_3ddb956bfc_t.jpg", "url": "http://www.flickr.com/photos/biblarte/2958169439/sizes/t/", "media": "photo", "height": "71", "width": "100", "label": "Thumbnail"}, {"source": "http://farm4.staticflickr.com/3055/2958169439_3ddb956bfc_m.jpg", "url": "http://www.flickr.com/photos/biblarte/2958169439/sizes/s/", "media": "photo", "height": "170", "width": "240", "label": "Small"}, {"source": "http://farm4.staticflickr.com/3055/2958169439_3ddb956bfc_n.jpg", "url": "http://www.flickr.com/photos/biblarte/2958169439/sizes/n/", "media": "photo", "height": 227, "width": "320", "label": "Small 320"}, {"source": "http://farm4.staticflickr.com/3055/2958169439_3ddb956bfc.jpg", "url": "http://www.flickr.com/photos/biblarte/2958169439/sizes/m/", "media": "photo", "height": "354", "width": "500", "label": "Medium"}, {"source": "http://farm4.staticflickr.com/3055/2958169439_3ddb956bfc_z.jpg", "url": "http://www.flickr.com/photos/biblarte/2958169439/sizes/z/", "media": "photo", "height": 453, "width": "640", "label": "Medium 640"}, {"source": "http://farm4.staticflickr.com/3055/2958169439_3ddb956bfc_b.jpg", "url": "http://www.flickr.com/photos/biblarte/2958169439/sizes/l/", "media": "photo", "height": "725", "width": "1024", "label": "Large"}, {"source": "http://farm4.staticflickr.com/3055/2958169439_1112b6f3dc_o.jpg", "url": "http://www.flickr.com/photos/biblarte/2958169439/sizes/o/", "media": "photo", "height": "2171", "width": "3068", "label": "Original"}], "candownload": 1, "canprint": 0}}