{"stat": "ok", "comments": {"comment": [{"permalink": "http://www.flickr.com/photos/nlireland/8574543162/#comment72157633043598154", "realname": "", "path_alias": null, "author": "79549245@N06", "iconserver": "8129", "datecreate": "1363771930", "_content": "<a href=\"http://maps.google.ie/maps?q=o'connell+street+dublin&amp;hl=en&amp;ll=53.346908,-6.259059&amp;spn=0.000001,0.000711&amp;sll=-3.137759,-60.493355&amp;sspn=0.049707,0.090981&amp;t=h&amp;hq=o'connell+street+dublin&amp;z=21&amp;layer=c&amp;cbll=53.346908,-6.259059&amp;panoid=QSoJe639LDNBnKXWxxBRAw&amp;cbp=12,17.45,,0,-8.42\" rel=\"nofollow\">maps.google.ie/maps?q=o'connell+street+dublin&amp;hl=en&a...</a>", "authorname": "DannyM8", "id": "47267889-8574543162-72157633043598154", "iconfarm": 9}, {"permalink": "http://www.flickr.com/photos/nlireland/8574543162/#comment72157633043703548", "realname": "Niall McAuley", "path_alias": "gnmcauley", "author": "30369211@N00", "iconserver": "7453", "datecreate": "1363773433", "_content": "Changes since <a href=\"http://www.flickr.com/photos/nlireland/6779100870/\">Bona Fide Travellers:</a>\n\nThe DBC. The tall electric lights (1892 until 1903-1910 sometime). Where is the Gunpowder office signage gone? Railings around the O'Connell monument. Electric trams. Straw hats! Light coloured clothes. Ladies on bikes.", "authorname": "Niall McAuley", "id": "47267889-8574543162-72157633043703548", "iconfarm": 8}, {"permalink": "http://www.flickr.com/photos/nlireland/8574543162/#comment72157633043738072", "realname": "", "path_alias": "nlireland", "author": "47290943@N03", "iconserver": "5468", "datecreate": "1363773922", "_content": "And as [http://www.flickr.com/photos/79549245@N06] spotted, a dust cart spraying the street! We've never captured one of those in action before...", "authorname": "National Library of Ireland on The Commons", "id": "47267889-8574543162-72157633043738072", "iconfarm": 6}, {"permalink": "http://www.flickr.com/photos/nlireland/8574543162/#comment72157633039587513", "realname": "", "path_alias": null, "author": "79549245@N06", "iconserver": "8129", "datecreate": "1363775282", "_content": "Summer  I would think, the few parasols are for the sun rather than the rain. Strong shadows - someone will be able to tell the date and time of day!", "authorname": "DannyM8", "id": "47267889-8574543162-72157633039587513", "iconfarm": 9}, {"permalink": "http://www.flickr.com/photos/nlireland/8574543162/#comment72157633043851834", "realname": "", "path_alias": "beachcomberaustralia", "author": "32162360@N00", "iconserver": "3722", "datecreate": "1363775459", "_content": "[http://www.flickr.com/photos/79549245@N06] Someone thinks 14:43 (?) from the clock (see note).  Not 100% sure.", "authorname": "beachcomberaustralia", "id": "47267889-8574543162-72157633043851834", "iconfarm": 4}, {"permalink": "http://www.flickr.com/photos/nlireland/8574543162/#comment72157633043913774", "realname": "", "path_alias": null, "author": "79549245@N06", "iconserver": "8129", "datecreate": "1363776353", "_content": "[http://www.flickr.com/photos/beachcomberaustralia] You have much better eyesight than me (or a better screen!!)", "authorname": "DannyM8", "id": "47267889-8574543162-72157633043913774", "iconfarm": 9}, {"permalink": "http://www.flickr.com/photos/nlireland/8574543162/#comment72157633043930854", "realname": "Niall McAuley", "path_alias": "gnmcauley", "author": "30369211@N00", "iconserver": "7453", "datecreate": "1363776590", "_content": "Per <a href=\"http://en.wikipedia.org/wiki/Dublin_tramways\" rel=\"nofollow\">wikipedia</a>, the Donnybrook tram was electrified from Jan 1899.\n\nI think the Hatch St. tram (via Westland Row) #22, electrified Jan 1900.", "authorname": "Niall McAuley", "id": "47267889-8574543162-72157633043930854", "iconfarm": 8}, {"permalink": "http://www.flickr.com/photos/nlireland/8574543162/#comment72157633039701003", "realname": "Niall McAuley", "path_alias": "gnmcauley", "author": "30369211@N00", "iconserver": "7453", "datecreate": "1363776830", "_content": "The DBC seems to have hoardings up at street level. I think it is not finished, and that this is Summer 1900.", "authorname": "Niall McAuley", "id": "47267889-8574543162-72157633039701003", "iconfarm": 8}, {"permalink": "http://www.flickr.com/photos/nlireland/8574543162/#comment72157633039806297", "realname": "", "path_alias": "swordscookie", "author": "39191857@N05", "iconserver": "3461", "datecreate": "1363778229", "_content": "The clarity of the shot is remarkable with a great DOF!  You can see that the policeman is in full regalia with his &quot;day&quot; helmet and at his wrist is his &quot;Duty&quot; band showing that he is on duty.\nUnusually the street traders on the near side of the Liffey are men!  On the far side the stall appears to be manned by a woman.  Right beside her a lady is dragging a reluctant urchin along to Clery's for his First Communion suit!  That just shows how good this shot is:-)\nNeaves food was very much on sale when I was a nipper and I think right up to the late 50's at leaset", "authorname": "swordscookie", "id": "47267889-8574543162-72157633039806297", "iconfarm": 4}, {"permalink": "http://www.flickr.com/photos/nlireland/8574543162/#comment72157633039875551", "realname": "", "path_alias": null, "author": "8468254@N02", "iconserver": "232", "datecreate": "1363779021", "_content": "wrt shadows: The sun app says end of May or end of August - About 30 days from the solstice either side. (Assuming that the time is 14:43).", "authorname": "derangedlemur", "id": "47267889-8574543162-72157633039875551", "iconfarm": 1}, {"permalink": "http://www.flickr.com/photos/nlireland/8574543162/#comment72157633044150964", "realname": "", "path_alias": "johnspooner", "author": "29809546@N00", "iconserver": "8104", "datecreate": "1363779281", "_content": "Those two ladies on bicycles had better watch out!\n\n<a href=\"http://www.flickr.com/photos/89773100@N02/8573689105/\">The drivers of DBC vans don't look where they are going</a>  (1899)", "authorname": "John Spooner", "id": "47267889-8574543162-72157633044150964", "iconfarm": 9}, {"permalink": "http://www.flickr.com/photos/nlireland/8574543162/#comment72157633040034339", "realname": "", "path_alias": "johnspooner", "author": "29809546@N00", "iconserver": "8104", "datecreate": "1363781004", "_content": "[http://www.flickr.com/photos/gnmcauley] The fruit stall in the foreground can just be seen in the Bona Fide Travellers picture. Or at least what look as if they might be some items of fruit can bee seen. I assume it's not the same fruit.", "authorname": "John Spooner", "id": "47267889-8574543162-72157633040034339", "iconfarm": 9}, {"permalink": "http://www.flickr.com/photos/nlireland/8574543162/#comment72157633044381002", "realname": "Niall McAuley", "path_alias": "gnmcauley", "author": "30369211@N00", "iconserver": "7453", "datecreate": "1363781947", "_content": "9th shot in <a href=\"http://dublincitypubliclibraries.com/image-galleries/digital-collections/dublin-shops-and-shopping\" rel=\"nofollow\">this gallery</a>: Wallace Bros Coal and Coke, 2 D'Olier St.", "authorname": "Niall McAuley", "id": "47267889-8574543162-72157633044381002", "iconfarm": 8}, {"permalink": "http://www.flickr.com/photos/nlireland/8574543162/#comment72157633040192527", "realname": "", "path_alias": "johnspooner", "author": "29809546@N00", "iconserver": "8104", "datecreate": "1363782511", "_content": "With regard to the design of the DBC building, a Keystone-Kops account of a small fire at the DBC restaurant at 33 Dame Street on Sept 6 1898 ('FIre and Fiasco in the City - Overzealous  Citizens - Smash fire escape') says\n<blockquote><i> The kitchen, as in most modern establishments carrying on a restaurant business, like the Dublin Bakery </i>[or should it be Bread?] <i> Company does, is situated at the top of the house, with a view to preserve the dinner and luncheon rooms from too high a temperature </i></blockquote>\nso I assume the one in the picture would be designed on the same principles, with the kitchens at the top. Would food be delivered by means of a movable boudoir?\n\nI was hoping streetview might show reveal something interesting at 33 Dame Street, but it looks as if the facade has been modernised, unlike some of its neighbours. <a href=\"https://maps.google.com/maps?q=Dame+Street,+Dublin,+Ireland&amp;hl=en&amp;ll=53.344211,-6.263645&amp;spn=0.010146,0.027874&amp;sll=53.349805,-6.26031&amp;sspn=0.649251,1.783905&amp;oq=dame+street&amp;hnear=Dame+St,+Dublin,+County+Dublin,+Ireland&amp;t=m&amp;z=16&amp;layer=c&amp;cbll=53.344226,-6.263296&amp;panoid=vxx_Wz8A88OqHWlNrfoOZg&amp;cbp=12,168.24474029999988,,0,-10.6949638&amp;photoid=pg-WIFH8vz6E31FSojtlNrCkw\" rel=\"nofollow\">Streetview</a>. \n\nDBC also had tea rooms at Kingstown station, described as 'new' in an account of a fire on June 25th 1900", "authorname": "John Spooner", "id": "47267889-8574543162-72157633040192527", "iconfarm": 9}, {"permalink": "http://www.flickr.com/photos/nlireland/8574543162/#comment72157633040319191", "realname": "", "path_alias": "johnspooner", "author": "29809546@N00", "iconserver": "8104", "datecreate": "1363783981", "_content": "Freeman's Tuesday 21st August 1900\n<a href=\"http://www.flickr.com/photos/89773100@N02/8573833879/\" title=\"dbc3 by JS presscuttings, on Flickr\"><img src=\"http://farm9.staticflickr.com/8234/8573833879_45738cca62.jpg\" width=\"245\" height=\"223\" alt=\"dbc3\" /></a>", "authorname": "John Spooner", "id": "47267889-8574543162-72157633040319191", "iconfarm": 9}, {"permalink": "http://www.flickr.com/photos/nlireland/8574543162/#comment72157633044998120", "realname": "", "path_alias": null, "author": "44274283@N07", "iconserver": "5327", "datecreate": "1363788459", "_content": "[http://www.flickr.com/photos/johnspooner] \n\nThat might account for the strangely tall roof.... Perhaps to help ventilate it....", "authorname": "Subpopulus Hibernia", "id": "47267889-8574543162-72157633044998120", "iconfarm": 6}, {"permalink": "http://www.flickr.com/photos/nlireland/8574543162/#comment72157633041007493", "realname": "", "path_alias": "gj94025", "author": "75116182@N04", "iconserver": "7059", "datecreate": "1363790757", "_content": "Nice shot!", "authorname": "Sole & Luna", "id": "47267889-8574543162-72157633041007493", "iconfarm": 8}, {"permalink": "http://www.flickr.com/photos/nlireland/8574543162/#comment72157633041357295", "realname": "", "path_alias": null, "author": "91549360@N03", "iconserver": "2827", "datecreate": "1363793807", "_content": "[http://www.flickr.com/photos/johnspooner]  Maybe a dumb waiter caused the 'small fire' mentioned in your account above. :)", "authorname": "OwenMacC", "id": "47267889-8574543162-72157633041357295", "iconfarm": 3}, {"permalink": "http://www.flickr.com/photos/nlireland/8574543162/#comment72157633041629525", "realname": "", "path_alias": "johnspooner", "author": "29809546@N00", "iconserver": "8104", "datecreate": "1363796058", "_content": "[http://www.flickr.com/photos/91549360@N03] Ha ha.  A 'movable cuisine', perhaps.\nA dumb cook, more like, who had put a mixture of beeswax and turpentine on the fire to heat.\n<a href=\"http://www.flickr.com/photos/89773100@N02/8575399022/sizes/o/in/photostream/\">Details here</a> [includes references to 'meddlesome boys' and a 'frightened quartette of females']\n\nI wonder what recipe requires beeswax and turpentine? If I'd read that it might put me off ever using DBC's Dame Street luncheon rooms.", "authorname": "John Spooner", "id": "47267889-8574543162-72157633041629525", "iconfarm": 9}, {"permalink": "http://www.flickr.com/photos/nlireland/8574543162/#comment72157633041698281", "realname": "", "path_alias": "johnspooner", "author": "29809546@N00", "iconserver": "8104", "datecreate": "1363796641", "_content": "To answer my own question, beeswax and turpentine are mixed to make beeswax polish. The cook obviously hadn't seen <a href=\"http://www.honeyshop.co.uk/Polish1.htm\" rel=\"nofollow\">this website</a>", "authorname": "John Spooner", "id": "47267889-8574543162-72157633041698281", "iconfarm": 9}, {"permalink": "http://www.flickr.com/photos/nlireland/8574543162/#comment72157633045967336", "realname": "", "path_alias": "vab2009", "author": "30622421@N03", "iconserver": "8533", "datecreate": "1363796923", "_content": "I agree about the clarity of this - it is stunning, and so much happening in it! Like being flipped back in time!", "authorname": "Vab2009", "id": "47267889-8574543162-72157633045967336", "iconfarm": 9}, {"permalink": "http://www.flickr.com/photos/nlireland/8574543162/#comment72157633042010709", "realname": "Dora Meulman", "path_alias": "dorameulman", "author": "59941010@N06", "iconserver": "2852", "datecreate": "1363798929", "_content": "Brilliant photo.", "authorname": "dorameulman", "id": "47267889-8574543162-72157633042010709", "iconfarm": 3}, {"permalink": "http://www.flickr.com/photos/nlireland/8574543162/#comment72157633042155267", "realname": "", "path_alias": null, "author": "20727502@N00", "iconserver": "7070", "datecreate": "1363800222", "_content": "[http://www.flickr.com/photos/johnspooner] Thanks for the link to the fire article. Very entertaining read. Possibly because of the repeated (if bizarre in today's terms) &quot;naming and shaming&quot; of the hapless citizens who are held up to mockery for their differing levels of involvement. One of the &quot;frightened quartette&quot; of ladies mentioned likely went home to recount her tale in <a href=\"http://www.census.nationalarchives.ie/pages/1901/Dublin/Fitzwilliam/Camden_Street_Lower/1305669/\" rel=\"nofollow\">Camden Street</a>.", "authorname": "guliolopez", "id": "47267889-8574543162-72157633042155267", "iconfarm": 8}, {"permalink": "http://www.flickr.com/photos/nlireland/8574543162/#comment72157633042281195", "realname": "", "path_alias": "swordscookie", "author": "39191857@N05", "iconserver": "3461", "datecreate": "1363801343", "_content": "[http://www.flickr.com/photos/johnspooner] Wonderful article showing that the forces of law and order are not only brave but versatile as well.  134B must have been off his beat if he did not give his name to the intrepid reporter!  The Garda museum might be able to identify the officers concerned from the old DMP Register in its custody!  Both numbers are still alive and active in the nearby Pearse Street station!", "authorname": "swordscookie", "id": "47267889-8574543162-72157633042281195", "iconfarm": 4}, {"permalink": "http://www.flickr.com/photos/nlireland/8574543162/#comment72157633043820559", "realname": "", "path_alias": "nlireland", "author": "47290943@N03", "iconserver": "5468", "datecreate": "1363817262", "_content": "Did you all know that you are &quot;an active user group&quot;, according to the <a href=\"http://www.bjp-online.com/british-journal-of-photography/report/2250132/shared-history-the-commons-initiative-celebrates-its-fifth-anniversary\" rel=\"nofollow\" target=\"_blank\"><b>British Journal of Photography</b></a>?   :)", "authorname": "National Library of Ireland on The Commons", "id": "47267889-8574543162-72157633043820559", "iconfarm": 6}, {"permalink": "http://www.flickr.com/photos/nlireland/8574543162/#comment72157633048109020", "realname": "", "path_alias": "johnspooner", "author": "29809546@N00", "iconserver": "8104", "datecreate": "1363817793", "_content": "[http://www.flickr.com/photos/nlireland] Because we're subject to &quot;active cultivation&quot;. I'm not as active as I should be - I spend far too much time sitting at a screen staring at old B&amp;W photos.", "authorname": "John Spooner", "id": "47267889-8574543162-72157633048109020", "iconfarm": 9}, {"permalink": "http://www.flickr.com/photos/nlireland/8574543162/#comment72157633050682316", "realname": "", "path_alias": "beachcomberaustralia", "author": "32162360@N00", "iconserver": "3722", "datecreate": "1363848692", "_content": "[http://www.flickr.com/photos/nlireland] Golly I loathe jargon, particularly &quot;crowdsource&quot; - I find it patronising and offensive, like <i>hoi polloi</i>.  Not much interesting and enlightening ever came from a crowd.  Or a committee.   We are reasonably intelligent individuals working on our own, and gaining further knowledge and pleasure from shared information.  End of rant.", "authorname": "beachcomberaustralia", "id": "47267889-8574543162-72157633050682316", "iconfarm": 4}, {"permalink": "http://www.flickr.com/photos/nlireland/8574543162/#comment72157633050790974", "realname": "", "path_alias": null, "author": "8468254@N02", "iconserver": "232", "datecreate": "1363850023", "_content": "[http://www.flickr.com/photos/nlireland] Hyperactive, I'd have said.", "authorname": "derangedlemur", "id": "47267889-8574543162-72157633050790974", "iconfarm": 1}, {"permalink": "http://www.flickr.com/photos/nlireland/8574543162/#comment72157633051246998", "realname": "Niall McAuley", "path_alias": "gnmcauley", "author": "30369211@N00", "iconserver": "7453", "datecreate": "1363855652", "_content": "[http://www.flickr.com/photos/91549360@N03]  That postcard looks to be the very same period: DBC, no Gunpowder office signs, tall streetlights, electric trams, ladies in bright clothes, lady with a bicycle...", "authorname": "Niall McAuley", "id": "47267889-8574543162-72157633051246998", "iconfarm": 8}, {"permalink": "http://www.flickr.com/photos/nlireland/8574543162/#comment72157633051298942", "realname": "", "path_alias": "nlireland", "author": "47290943@N03", "iconserver": "5468", "datecreate": "1363856355", "_content": "[http://www.flickr.com/photos/beachcomberaustralia] &quot;We are reasonably intelligent individuals working on our own, and gaining further knowledge and pleasure from shared information&quot; and composing Limericks!  :)", "authorname": "National Library of Ireland on The Commons", "id": "47267889-8574543162-72157633051298942", "iconfarm": 6}, {"permalink": "http://www.flickr.com/photos/nlireland/8574543162/#comment72157633052161808", "realname": "", "path_alias": "swordscookie", "author": "39191857@N05", "iconserver": "3461", "datecreate": "1363867039", "_content": "[http://www.flickr.com/photos/nlireland/] I was beginning to think that we are hypersensitive:-)", "authorname": "swordscookie", "id": "47267889-8574543162-72157633052161808", "iconfarm": 4}, {"permalink": "http://www.flickr.com/photos/nlireland/8574543162/#comment72157633047931273", "realname": "", "path_alias": "swordscookie", "author": "39191857@N05", "iconserver": "3461", "datecreate": "1363867312", "_content": "[http://www.flickr.com/photos/nlireland/] I didn't realise that you were &quot;actively cultivating an audience&quot;. I thought you were enjoying the Craic.  Seriously when you read this I realise how much we owe to your moderation of the stream and the brilliant contributors who put so much into the chase, this site is brilliant!!!!!!", "authorname": "swordscookie", "id": "47267889-8574543162-72157633047931273", "iconfarm": 4}, {"permalink": "http://www.flickr.com/photos/nlireland/8574543162/#comment72157633052264712", "realname": "", "path_alias": "johnspooner", "author": "29809546@N00", "iconserver": "8104", "datecreate": "1363868215", "_content": "[http://www.flickr.com/photos/swordscookie] Quite so . Compare it, for example, to <a href=\"http://www.flickr.com/photos/llgc/\">The National Library of Wales' photostream</a>  - they have some fascinating photos, but the last 12 photos posted have garnered a total of 2 comments between them. I think we all know <s>what</s> who makes the difference.", "authorname": "John Spooner", "id": "47267889-8574543162-72157633052264712", "iconfarm": 9}, {"permalink": "http://www.flickr.com/photos/nlireland/8574543162/#comment72157633052280372", "realname": "", "path_alias": "johnspooner", "author": "29809546@N00", "iconserver": "8104", "datecreate": "1363868397", "_content": "[http://www.flickr.com/photos/nlireland] [http://www.flickr.com/photos/beachcomberaustralia] I think you mean: &quot;We are (a crowd of) reasonably intelligent individuals ...&quot; :)", "authorname": "John Spooner", "id": "47267889-8574543162-72157633052280372", "iconfarm": 9}, {"permalink": "http://www.flickr.com/photos/nlireland/8574543162/#comment72157633048177879", "realname": "Niall McAuley", "path_alias": "gnmcauley", "author": "30369211@N00", "iconserver": "7453", "datecreate": "1363869900", "_content": "[http://www.flickr.com/photos/johnspooner] And one of those 2 comments is from you!", "authorname": "Niall McAuley", "id": "47267889-8574543162-72157633048177879", "iconfarm": 8}, {"permalink": "http://www.flickr.com/photos/nlireland/8574543162/#comment72157633052464390", "realname": "", "path_alias": "johnspooner", "author": "29809546@N00", "iconserver": "8104", "datecreate": "1363870284", "_content": "[http://www.flickr.com/photos/gnmcauley] But it was just begging for a streetview comparison, wasn't it? Especially as I cycle past that spot every year (18th May this year)", "authorname": "John Spooner", "id": "47267889-8574543162-72157633052464390", "iconfarm": 9}, {"permalink": "http://www.flickr.com/photos/nlireland/8574543162/#comment72157633052632102", "realname": "", "path_alias": "nlireland", "author": "47290943@N03", "iconserver": "5468", "datecreate": "1363872006", "_content": "[http://www.flickr.com/photos/gnmcauley] What's this? [http://www.flickr.com/photos/johnspooner] is being unfaithful to us, gadding about all over? Humph!", "authorname": "National Library of Ireland on The Commons", "id": "47267889-8574543162-72157633052632102", "iconfarm": 6}, {"permalink": "http://www.flickr.com/photos/nlireland/8574543162/#comment72157633052715242", "realname": "", "path_alias": "nlireland", "author": "47290943@N03", "iconserver": "5468", "datecreate": "1363872670", "_content": "[http://www.flickr.com/photos/swordscookie] No, <b>you're</b> all brilliant!  :)", "authorname": "National Library of Ireland on The Commons", "id": "47267889-8574543162-72157633052715242", "iconfarm": 6}, {"permalink": "http://www.flickr.com/photos/nlireland/8574543162/#comment72157633048514319", "realname": "", "path_alias": "johnspooner", "author": "29809546@N00", "iconserver": "8104", "datecreate": "1363872897", "_content": "[http://www.flickr.com/photos/nlireland] I'm not normally one to grass anyone up, but that [http://www.flickr.com/photos/beachcomberaustralia] leaves his comments all over the place. But  to be fair he does restrict his limericks to the appropriate locality.", "authorname": "John Spooner", "id": "47267889-8574543162-72157633048514319", "iconfarm": 9}, {"permalink": "http://www.flickr.com/photos/nlireland/8574543162/#comment72157633054612432", "realname": "", "path_alias": null, "author": "79549245@N06", "iconserver": "8129", "datecreate": "1363886409", "_content": "[http://www.flickr.com/photos/nlireland] When are we having our &quot;active user group&quot; <b>OUTING </b>, to Wesport or Newport or Limerick or Cork or Adrigole or Birr or Belfast or Molls Gap or Donnybrook or Terenure or .............................................................................", "authorname": "DannyM8", "id": "47267889-8574543162-72157633054612432", "iconfarm": 9}, {"permalink": "http://www.flickr.com/photos/nlireland/8574543162/#comment72157633056358140", "realname": "", "path_alias": null, "author": "8468254@N02", "iconserver": "232", "datecreate": "1363900700", "_content": "[http://www.flickr.com/photos/79549245@N06] We should have a magical mystery tour. To Larne.", "authorname": "derangedlemur", "id": "47267889-8574543162-72157633056358140", "iconfarm": 1}, {"permalink": "http://www.flickr.com/photos/nlireland/8574543162/#comment72157633052152071", "realname": "", "path_alias": null, "author": "33546386@N03", "iconserver": "2807", "datecreate": "1363901012", "_content": "EXCELLENT In One word !\nMy Compliments", "authorname": "excellentzebu1050", "id": "47267889-8574543162-72157633052152071", "iconfarm": 3}, {"permalink": "http://www.flickr.com/photos/nlireland/8574543162/#comment72157633052353033", "realname": "", "path_alias": "beachcomberaustralia", "author": "32162360@N00", "iconserver": "3722", "datecreate": "1363902720", "_content": "[http://www.flickr.com/photos/nlireland] [http://www.flickr.com/photos/johnspooner] Guilty as charged! \n\n[http://www.flickr.com/photos/8468254@N02] I spent a virtual life sentence in Larne one day.\n\n[http://www.flickr.com/photos/33546386@N03] That's six words! - not that I'm counting ...\n\nMeanwhile, back at the photo - it looks like there is a temporary fence in front of the DBC building implying it has not opened yet, but is just about to.  I vote for <b>late August 1900</b> due to [http://www.flickr.com/photos/8468254@N02]'s shadow thingy, and [http://www.flickr.com/photos/johnspooner]'s 21/8/1900 advert (above).", "authorname": "beachcomberaustralia", "id": "47267889-8574543162-72157633052353033", "iconfarm": 4}, {"permalink": "http://www.flickr.com/photos/nlireland/8574543162/#comment72157633056474255", "realname": "Richard Cowdell", "path_alias": null, "author": "56225952@N06", "iconserver": "4131", "datecreate": "1363950775", "_content": "Apologies to all Joyceans - On the last picture of the DBC I misquoted James Joyce's Ulysses. The quotation (from 'Wandering Rocks') is &quot;We call it D.B.C. because they have damn bad cakes. O, but you missed Dedalus on Hamlet&quot;. I'm just in my annual reading of the novel.", "authorname": "richard39a", "id": "47267889-8574543162-72157633056474255", "iconfarm": 5}, {"permalink": "http://www.flickr.com/photos/nlireland/8574543162/#comment72157633061034800", "realname": "", "path_alias": "nlireland", "author": "47290943@N03", "iconserver": "5468", "datecreate": "1363954740", "_content": "Happy to go with August 1900!", "authorname": "National Library of Ireland on The Commons", "id": "47267889-8574543162-72157633061034800", "iconfarm": 6}, {"permalink": "http://www.flickr.com/photos/nlireland/8574543162/#comment72157633073210728", "realname": "", "path_alias": "beachcomberaustralia", "author": "32162360@N00", "iconserver": "3722", "datecreate": "1364074150", "_content": "[http://www.flickr.com/photos/91549360@N03] Using the contemporary weather reports to date photos seems sensible and reliable to me.  Why not?  Or at least to confirm dates. But if there were <a href=\"http://en.wikipedia.org/wiki/Anticyclone\" rel=\"nofollow\">anticyclones</a> centred over Europe it would surely produce south-easterly (ie warm and dry) winds in Ireland - hence the summer clothes on the folk and the sprinkling water-cart.  Also there is a convenient large flag just to the right of Nelson's Pillar which seems to show a stiff breeze from the south-east - if Sackville Street runs roughly NNW-SSE.   \n\nHot and cross virtual sticky buns at the DBC!", "authorname": "beachcomberaustralia", "id": "47267889-8574543162-72157633073210728", "iconfarm": 4}, {"permalink": "http://www.flickr.com/photos/nlireland/8574543162/#comment72157633069914053", "realname": "", "path_alias": "johnspooner", "author": "29809546@N00", "iconserver": "8104", "datecreate": "1364082063", "_content": "Freeman's reported 'constant wet weather for the last fortnight' on 15th August <b>1900</b>, which was endangering the harvest, but on the 17th 'propitious weather' was reported at Ballyboden Cottage Show and a cricket match between Richmond Asylum and The Druids was played in 'glorious weather'. On the same say it was reported that a labourer named John Lee was taken to Jervis street hospital and diagnosed as suffering from 'heat apoplexy'. Spectators at Dundrum sports earlier in the week had enjoyed 'scorching hot' weather.\n\nA report under the heading 'Yachting' on Monday 20th says 'Saturday, although a suitable and glorious day for all sports, was a little too fine for yachting, and out of a big list of sailing fixtures at Howth and Kingstown but one race was completed. The light breeze of the forenoon failed almost altogether in the afternoon, and all the racers were hopelessly becalmed for some hours'.", "authorname": "John Spooner", "id": "47267889-8574543162-72157633069914053", "iconfarm": 9}, {"permalink": "http://www.flickr.com/photos/nlireland/8574543162/#comment72157633077083850", "realname": "", "path_alias": null, "author": "8468254@N02", "iconserver": "232", "datecreate": "1364116758", "_content": "I think the only thing stopping us until now has been getting accurate reports, but you seem to have solved that one.", "authorname": "derangedlemur", "id": "47267889-8574543162-72157633077083850", "iconfarm": 1}, {"permalink": "http://www.flickr.com/photos/nlireland/8574543162/#comment72157633073360841", "realname": "", "path_alias": "johnspooner", "author": "29809546@N00", "iconserver": "8104", "datecreate": "1364122342", "_content": "<s>In its daily 'Shipping Intelligence' column, Freeman's has a one-line summary of the previous day's Dublin weather, with wind direction &amp; strength, one or two words of general description  (e.g. fine, showery) and barometric pressure. I've put August 1890's entries on\n<a href=\"https://docs.google.com/spreadsheet/pub?key=0AnhkQtpa91GSdE54UVlzeWpNaVFjV19IemczUV8tenc&amp;output=html\" rel=\"nofollow\">a spreadsheet</a>\n\nThe observations seem to agree the other data we have - the window of fine weather was from the 16th to the 20th or 21st..</s> Please ignore.", "authorname": "John Spooner", "id": "47267889-8574543162-72157633073360841", "iconfarm": 9}, {"permalink": "http://www.flickr.com/photos/nlireland/8574543162/#comment72157633073489155", "realname": "", "path_alias": null, "author": "91549360@N03", "iconserver": "2827", "datecreate": "1364123616", "_content": "[http://www.flickr.com/photos/johnspooner]  1890?", "authorname": "OwenMacC", "id": "47267889-8574543162-72157633073489155", "iconfarm": 3}, {"permalink": "http://www.flickr.com/photos/nlireland/8574543162/#comment72157633077813332", "realname": "", "path_alias": "johnspooner", "author": "29809546@N00", "iconserver": "8104", "datecreate": "1364124369", "_content": "[http://www.flickr.com/photos/91549360@N03] AAAAAAGH", "authorname": "John Spooner", "id": "47267889-8574543162-72157633077813332", "iconfarm": 9}, {"permalink": "http://www.flickr.com/photos/nlireland/8574543162/#comment72157633078052882", "realname": "", "path_alias": "johnspooner", "author": "29809546@N00", "iconserver": "8104", "datecreate": "1364126650", "_content": "<a href=\"https://docs.google.com/spreadsheet/pub?key=0AnhkQtpa91GSdEozU28tQmNtRk9xU25fLVVITXAwa1E&amp;output=html\" rel=\"nofollow\">Dublin weather August <b>1900</b></a>\n\nA  report on the Greystones tennis tournament backs this up  (i.e. that the fine spell began on the 11th) - &quot;This tournament continued on Saturday, when the weather favourably contrasted with that of the previous days of the tournament&quot; (although I'm not convinced it was played on consecutive days). The tournament had begun a week earlier but  &quot;Owing to recent heavy rain the courts were somewhat soft&quot;.", "authorname": "John Spooner", "id": "47267889-8574543162-72157633078052882", "iconfarm": 9}, {"permalink": "http://www.flickr.com/photos/nlireland/8574543162/#comment72157633078109836", "realname": "", "path_alias": null, "author": "8468254@N02", "iconserver": "232", "datecreate": "1364127182", "_content": "Well, 20th was where the shadows put it, but again, that's by eye, rather than measured. It could be a couple of weeks either side. The fruit barrow, being square, gives a pretty clear sun direction and height though.", "authorname": "derangedlemur", "id": "47267889-8574543162-72157633078109836", "iconfarm": 1}, {"permalink": "http://www.flickr.com/photos/nlireland/8574543162/#comment72157633076108205", "realname": "", "path_alias": "johnspooner", "author": "29809546@N00", "iconserver": "8104", "datecreate": "1364144022", "_content": "I wonder how many consecutive dry days before the street sprinkler is required to damp down the dust?", "authorname": "John Spooner", "id": "47267889-8574543162-72157633076108205", "iconfarm": 9}, {"permalink": "http://www.flickr.com/photos/nlireland/8574543162/#comment72157633076320001", "realname": "", "path_alias": "johnspooner", "author": "29809546@N00", "iconserver": "8104", "datecreate": "1364145574", "_content": "[http://www.flickr.com/photos/91549360@N03] I wouldn't argue with any of that.", "authorname": "John Spooner", "id": "47267889-8574543162-72157633076320001", "iconfarm": 9}, {"permalink": "http://www.flickr.com/photos/nlireland/8574543162/#comment72157633080670152", "realname": "", "path_alias": "johnspooner", "author": "29809546@N00", "iconserver": "8104", "datecreate": "1364146194", "_content": "I've given up waiting for a Limerick, so here's the result when \n\n<i>The street-sprinkler recently set his Muse to work, with the following charming result:-\n<blockquote>Throughout the hot and dusty day\nThe sprinkling sprinkler sprinks its way,\nAnd sprinkles sprinklings up and down\nThe sprinkful precincts of the town.\nIn vain have sprinkled ladies swore\nAt crossings sprinkly sprinkled o'er;\nIn vain the sprightly sprinkling hoots \nWho sees the sprinkler sprink his boots;\nThat sprinkling sprinkler sprinkles on\nUntil its sprinkling sprink is done,\nNor pauses for a curse or thank\nUntil its final sprink is sprank.</blockquote></i>\n (The Preston Guardian, Saturday, August 23, 1879)", "authorname": "John Spooner", "id": "47267889-8574543162-72157633080670152", "iconfarm": 9}, {"permalink": "http://www.flickr.com/photos/nlireland/8574543162/#comment72157633078310697", "realname": "", "path_alias": "johnspooner", "author": "29809546@N00", "iconserver": "8104", "datecreate": "1364159119", "_content": "I can't quite make out what is in the window of Hopkins &amp; Hopkins. The advert placed in Freemans on 17th August 1900 tells us what we can expect to see in a few days - A massive solid silver tray and table lamp, a  handsome gold chain bracelet and a solid silver Irish 2-handled challenge cup.\n\n<a href=\"http://www.flickr.com/photos/89773100@N02/8586350521/\">Hopkins &amp; Hopkins advert</a>", "authorname": "John Spooner", "id": "47267889-8574543162-72157633078310697", "iconfarm": 9}, {"permalink": "http://www.flickr.com/photos/nlireland/8574543162/#comment72157633086407906", "realname": "", "path_alias": null, "author": "8468254@N02", "iconserver": "232", "datecreate": "1364196282", "_content": "Of course our musings aren't helped by the fact that I've got a typo in my first shadow post which I've then repeated later. It's around the 20th of July, not August.", "authorname": "derangedlemur", "id": "47267889-8574543162-72157633086407906", "iconfarm": 1}, {"permalink": "http://www.flickr.com/photos/nlireland/8574543162/#comment72157633086881636", "realname": "", "path_alias": "beachcomberaustralia", "author": "32162360@N00", "iconserver": "3722", "datecreate": "1364203930", "_content": "[http://www.flickr.com/photos/8468254@N02] Ooops! Can you check the clock-on-the-right time too,  please?  I fiddled around with the photo not very successfully in picasa - could be wrong with 14:43.", "authorname": "beachcomberaustralia", "id": "47267889-8574543162-72157633086881636", "iconfarm": 4}, {"permalink": "http://www.flickr.com/photos/nlireland/8574543162/#comment72157633086912104", "realname": "", "path_alias": "beachcomberaustralia", "author": "32162360@N00", "iconserver": "3722", "datecreate": "1364204404", "_content": "<blockquote>\n<u>The Dublin Bread Company Limerick</u>\n\nIt's almost a quarter to three\nWe could do with a nice cup of tea.\nLet's sprinkle our feet\nAs we stroll up the street -\nFor hot buns at the new D. B. C.\n</blockquote>", "authorname": "beachcomberaustralia", "id": "47267889-8574543162-72157633086912104", "iconfarm": 4}, {"permalink": "http://www.flickr.com/photos/nlireland/8574543162/#comment72157633083105185", "realname": "", "path_alias": null, "author": "8468254@N02", "iconserver": "232", "datecreate": "1364210755", "_content": "[http://www.flickr.com/photos/beachcomberaustralia] There's no time of day that could make it the 20th of August. The sun is too high.", "authorname": "derangedlemur", "id": "47267889-8574543162-72157633083105185", "iconfarm": 1}, {"permalink": "http://www.flickr.com/photos/nlireland/8574543162/#comment72157633087650068", "realname": "", "path_alias": "johnspooner", "author": "29809546@N00", "iconserver": "8104", "datecreate": "1364214279", "_content": "[http://www.flickr.com/photos/beachcomberaustralia] I knew you'd come up trumps!\n\nMeanwhile, <a href=\"https://docs.google.com/spreadsheet/pub?key=0AnhkQtpa91GSdEozU28tQmNtRk9xU25fLVVITXAwa1E&amp;single=true&amp;gid=1&amp;output=html\" rel=\"nofollow\">Dublin  weather July 1900</a> Not as clear-cut as August.", "authorname": "John Spooner", "id": "47267889-8574543162-72157633087650068", "iconfarm": 9}, {"permalink": "http://www.flickr.com/photos/nlireland/8574543162/#comment72157633087014411", "realname": "", "path_alias": "beachcomberaustralia", "author": "32162360@N00", "iconserver": "3722", "datecreate": "1364246168", "_content": "[http://www.flickr.com/photos/johnspooner] Thank you! I had &quot;tarts&quot; instead of ''buns&quot; at first ...\n\nRe The Weather - Thursday 19/7/1900 is looking good - &quot;fine, SE breezes&quot; and it hasn't rained in Dublin since 3 July ... good enough reason for a sprinkle.  Also the River Liffey looks low - undoubtedly the tide.  Aha! That gives me an idea - the Dublin tide times for July 1900 (at 14:43 -ish).  Where to find them ... ?", "authorname": "beachcomberaustralia", "id": "47267889-8574543162-72157633087014411", "iconfarm": 4}, {"permalink": "http://www.flickr.com/photos/nlireland/8574543162/#comment72157633087399717", "realname": "", "path_alias": "johnspooner", "author": "29809546@N00", "iconserver": "8104", "datecreate": "1364249568", "_content": "[http://www.flickr.com/photos/beachcomberaustralia]  High water at Dublin for July 1900\nJuly 4  03:25 &amp; 15:48\nJuly 5  04:12 &amp; 16:38\nJuly 6  05:08 &amp; 17:36\nJuly 7  06:05 &amp; 18:37\nJuly 10 09:09 &amp; 21:37\nJuly 1210:42 &amp; 23:04\nJuly 14 12:00 &amp; 00:10\nJuly 17 02:08 &amp; 14:33\nJuly 18 02:57 &amp; 15:23\nJuly 19 03:51 &amp; 16:18\nJuly 23 08:17 &amp; 20:50\nJuly 26 10:53 &amp; 23:12\nJuly 27 11:29 &amp; 23:46\nJuly 28 12:00 &amp; 00:05\nJuly 30 01:00 &amp; 13:15", "authorname": "John Spooner", "id": "47267889-8574543162-72157633087399717", "iconfarm": 9}, {"permalink": "http://www.flickr.com/photos/nlireland/8574543162/#comment72157633094311338", "realname": "", "path_alias": null, "author": "8468254@N02", "iconserver": "232", "datecreate": "1364281688", "_content": "I can't guarantee it from a still, but it looks like the tide is coming in, not going out, which would put it at less than six and a half hours from high water, or at a guess from the picture, about three hours before high water, which could really only be about the 20th or 21st, but that doesn't match the breeze direction, which looks easterly. It can't be the 22nd because there's too many shops open for a sunday. Let's have another look at the shadow machine...", "authorname": "derangedlemur", "id": "47267889-8574543162-72157633094311338", "iconfarm": 1}, {"permalink": "http://www.flickr.com/photos/nlireland/8574543162/#comment72157633090054803", "realname": "", "path_alias": null, "author": "8468254@N02", "iconserver": "232", "datecreate": "1364282091", "_content": "Of course, without daylight saving, what I'm seeing as three o'clock on the solar calculator would have been called two o'clock back then, so the tide could conceivably be 16:18.", "authorname": "derangedlemur", "id": "47267889-8574543162-72157633090054803", "iconfarm": 1}, {"permalink": "http://www.flickr.com/photos/nlireland/8574543162/#comment72157633094354940", "realname": "", "path_alias": null, "author": "8468254@N02", "iconserver": "232", "datecreate": "1364282269", "_content": "At this stage though, I'm starting to suspect an hour earlier in late June. The lack of readable clocks makes this difficult. If the clock really said 14:43, that'd make it 15:43 in today's money, and there's no way it's that late. If we therefore ignore the clock and go just with the shadows, it's 14:00 (new time - 13:00 1900-time) on the 26th June.", "authorname": "derangedlemur", "id": "47267889-8574543162-72157633094354940", "iconfarm": 1}, {"permalink": "http://www.flickr.com/photos/nlireland/8574543162/#comment72157633106062200", "realname": "", "path_alias": "abandonedminesofireland", "author": "94423390@N08", "iconserver": "0", "datecreate": "1364407996", "_content": "Really awesome photograph!", "authorname": "AbandonedMinesOfIreland", "id": "47267889-8574543162-72157633106062200", "iconfarm": 0}, {"permalink": "http://www.flickr.com/photos/nlireland/8574543162/#comment72157634238288197", "realname": "", "path_alias": null, "author": "94923461@N00", "iconserver": "7293", "datecreate": "1371789042", "_content": "Incredible you  can take  a lot of  fantastic  shots! :) &lt;3", "authorname": "JoeCow", "id": "47267889-8574543162-72157634238288197", "iconfarm": 8}, {"permalink": "http://www.flickr.com/photos/nlireland/8574543162/#comment72157634760472893", "realname": "Gabriel Harding", "path_alias": "gabrielharding", "author": "24143389@N03", "iconserver": "5339", "datecreate": "1374596833", "_content": "Awesomeeee", "authorname": "Gabriel Harding Photography", "id": "47267889-8574543162-72157634760472893", "iconfarm": 6}, {"permalink": "http://www.flickr.com/photos/nlireland/8574543162/#comment72157638889790443", "realname": "Olivier Jeannin", "path_alias": null, "author": "13151038@N02", "iconserver": "4002", "datecreate": "1387653814", "_content": "fantastic, I love it!", "authorname": "olivier.jeannin", "id": "47267889-8574543162-72157638889790443", "iconfarm": 5}], "photo_id": "8574543162"}}