{"stat": "ok", "comments": {"comment": [{"permalink": "http://www.flickr.com/photos/smu_cul_digitalcollections/6808058665/#comment72157633442208276", "realname": "Leroy Walther", "path_alias": null, "author": "27541657@N07", "iconserver": "0", "datecreate": "1367943972", "_content": "Not sure of description 'Three mile draw bridge' I always heard it called the Bascule draw bridge at the entrance to Corpus Christi port.  Sorry about the spelling 'bascule not sure it is correct", "authorname": "leetrace", "id": "41086171-6808058665-72157633442208276", "iconfarm": 0}], "photo_id": "6808058665"}, "flarchive:created": 1389683647}