{"photo": {"people": {"haspeople": 0}, "dateuploaded": "1276553974", "originalformat": "jpg", "owner": {"username": "SMU Central University Libraries", "realname": "", "nsid": "41131493@N06", "iconserver": "2886", "location": "", "path_alias": "smu_cul_digitalcollections", "iconfarm": 3}, "publiceditability": {"canaddmeta": 1, "cancomment": 1}, "id": "4701493284", "title": {"_content": "[Employees outside company office, Cananea office]"}, "media": "photo", "tags": {"tag": [{"raw": "mexico", "machine_tag": 0, "id": "41086171-4701493284-1725", "_content": "mexico", "author": "41131493@N06"}, {"raw": "mexicanrevolution", "machine_tag": 0, "id": "41086171-4701493284-751166", "_content": "mexicanrevolution", "author": "41131493@N06"}, {"raw": "cananea", "machine_tag": 0, "id": "41086171-4701493284-5887512", "_content": "cananea", "author": "41131493@N06"}]}, "comments": {"_content": "0"}, "secret": "fb916c1d39", "usage": {"canblog": 0, "canshare": 1, "candownload": 1, "canprint": 0}, "description": {"_content": "Title: [Employees outside company office, Cananea office] \nCreator: Great Western View Co. \nDate: 1906\nPart Of: Cananea, Mexico\n\nDescription: This photograph is part of the Cananea, Mexico collection which includes 20 photographs of Cananea, Mexico located just across the Arizona border showing striking miners, armed men, demonstrations, the mine site, town views and American company employees. Included are views of Colonel William C. Greene of Cananea Consolidated Copper Company addressing strikers, June 3, 1906. The conflict is considered a key event in the general unrest that emerged during the final years of the regime of President Porfirio Diaz and that prefigured the Mexican Revolution of 1910.    \n\nPhysical Description: 1 photographic print: gelatin silver, black and white; 12.7 x 17.8 cm. mounted 17.8 x 22.9 cm. \nForm/Genre: Photographs; Photographic prints \nFile: ag1983_0282_09_opt.tif \n\nRights: Please cite Southern Methodist University, Central University Libraries, DeGolyer Library when using this file. A high-quality version of this file may be obtained for a fee by contacting degolyer@smu.edu. \n\nFor more information, see: <a href=\"http://digitalcollections.smu.edu/u?/mex,177\" rel=\"nofollow\">digitalcollections.smu.edu/u?/mex,177</a>\n\nView Mexico: Photographs, Manuscripts, and Imprints at: <a href=\"http://digitalcollections.smu.edu/all/cul/mex/\" rel=\"nofollow\">digitalcollections.smu.edu/all/cul/mex/</a>"}, "isfavorite": 0, "views": "2927", "farm": 2, "visibility": {"isfriend": 0, "isfamily": 0, "ispublic": 1}, "rotation": 0, "dates": {"taken": "1906-06-01 00:00:00", "lastupdate": "1379641957", "takengranularity": "4", "posted": "1276553974"}, "originalsecret": "78c41a5aa0", "license": "7", "notes": {"note": []}, "server": "1286", "safety_level": "0", "urls": {"url": [{"type": "photopage", "_content": "http://www.flickr.com/photos/smu_cul_digitalcollections/4701493284/"}]}, "editability": {"canaddmeta": 0, "cancomment": 0}}, "stat": "ok", "flarchive:created": 1389685366}