{"stat": "ok", "comments": {"comment": [{"permalink": "http://www.flickr.com/photos/nasacommons/4858566616/#comment72157624718730565", "realname": "", "path_alias": "bagofarms", "author": "68846374@N00", "iconserver": "123", "datecreate": "1283201109", "_content": "Fitting that this picture was posted today, considering that ICESat was successfully deorbited this morning.", "authorname": "BagOfArms", "id": "44489032-4858566616-72157624718730565", "iconfarm": 1}, {"permalink": "http://www.flickr.com/photos/nasacommons/4858566616/#comment72157633405648433", "realname": "otis henry fijord (all or most ~", "path_alias": null, "author": "84575910@N06", "iconserver": "8489", "datecreate": "1367724826", "_content": "... ! !  PRIMO shot !", "authorname": "outside look", "id": "44489032-4858566616-72157633405648433", "iconfarm": 9}], "photo_id": "4858566616"}, "flarchive:created": 1387643361}