{"stat": "ok", "comments": {"comment": [{"permalink": "http://www.flickr.com/photos/library_of_congress/4119268687/#comment72157622717846471", "realname": "Henk van der Eijk", "path_alias": "anachronism_unltd", "author": "70889503@N00", "iconserver": "36", "datecreate": "1258734881", "_content": "Hi, I'm an admin for a group called <a href=\"http://www.flickr.com/groups/681783@N24/\">Historical Gardens</a>, and we'd love to have this added to the group!", "authorname": "Henk van der Eijk", "id": "8602872-4119268687-72157622717846471", "iconfarm": 1}, {"permalink": "http://www.flickr.com/photos/library_of_congress/4119268687/#comment72157622916417546", "realname": "", "path_alias": null, "author": "45239423@N08", "iconserver": "0", "datecreate": "1259714213", "_content": "This picture is beautiful! Not something anyone would ever see in the modern world!!", "authorname": "foundmysock1", "id": "8602872-4119268687-72157622916417546", "iconfarm": 0}, {"permalink": "http://www.flickr.com/photos/library_of_congress/4119268687/#comment72157634249574127", "realname": "", "path_alias": "mariemaramaroetjskaka", "author": "10603986@N05", "iconserver": "8344", "datecreate": "1371846808", "_content": "one big mistake, this ruin is not in Haarlem but in Santpoort .\nI've lived nearby for 45 years", "authorname": "Kaleidoscoop", "id": "8602872-4119268687-72157634249574127", "iconfarm": 9}, {"permalink": "http://www.flickr.com/photos/library_of_congress/4119268687/#comment72157634341644174", "realname": "Karen", "path_alias": "kchi_loc", "author": "34985608@N03", "iconserver": "3099", "datecreate": "1372256756", "_content": "Thanks for catching this error, Kaleidoscoop. Our title comes from the Detroit Publishing Co. but Brederode Castle does indeed appear to be in Santpoort. We will make a correction to our record next time we update.", "authorname": "kchi (LOC P&P)", "id": "8602872-4119268687-72157634341644174", "iconfarm": 4}, {"permalink": "http://www.flickr.com/photos/library_of_congress/4119268687/#comment72157634342395738", "realname": "", "path_alias": "mariemaramaroetjskaka", "author": "10603986@N05", "iconserver": "8344", "datecreate": "1372259966", "_content": "Well the text on the card sais Haarlem so how could you know?\nIn the time this card was made this part of Santpoort was called &quot;buurtschap Jan Gijzen&quot;.\nSince 1957 it is known as Santpoort Zuid", "authorname": "Kaleidoscoop", "id": "8602872-4119268687-72157634342395738", "iconfarm": 9}], "photo_id": "4119268687"}}