{"photo": {"people": {"haspeople": 0}, "dateuploaded": "1285687194", "originalformat": "jpg", "owner": {"username": "The National Archives UK", "realname": "", "nsid": "31575009@N05", "iconserver": "7325", "location": "", "path_alias": "nationalarchives", "iconfarm": 8}, "publiceditability": {"canaddmeta": 1, "cancomment": 1}, "id": "5033555370", "title": {"_content": "Pioneer Gunboat"}, "media": "photo", "tags": {"tag": [{"raw": "The National Archives (UK)", "machine_tag": 0, "id": "31569669-5033555370-30835915", "_content": "thenationalarchivesuk", "author": "31575009@N05"}, {"raw": "Admiralty", "machine_tag": 0, "id": "31569669-5033555370-110056", "_content": "admiralty", "author": "31575009@N05"}, {"raw": "New Zealand", "machine_tag": 0, "id": "31569669-5033555370-232", "_content": "newzealand", "author": "31575009@N05"}, {"raw": "tna:PieceReference=ADM101p239", "machine_tag": 1, "id": "31569669-5033555370-108886276", "_content": "tna:PieceReference=adm101p239", "author": "31575009@N05"}, {"raw": "tna:SubseriesReference=ADM101ss8", "machine_tag": 1, "id": "31569669-5033555370-108886278", "_content": "tna:SubseriesReference=adm101ss8", "author": "31575009@N05"}, {"raw": "tna:IAID=C10642669", "machine_tag": 1, "id": "31569669-5033555370-108886280", "_content": "tna:IAID=c10642669", "author": "31575009@N05"}, {"raw": "tna:ItemReference=ADM101p239i2", "machine_tag": 1, "id": "31569669-5033555370-108886282", "_content": "tna:ItemReference=adm101p239i2", "author": "31575009@N05"}, {"raw": "tna:SeriesReference=ADM101", "machine_tag": 1, "id": "31569669-5033555370-108878181", "_content": "tna:SeriesReference=adm101", "author": "31575009@N05"}, {"raw": "tna:DivisionReference=ADMd2", "machine_tag": 1, "id": "31569669-5033555370-108878183", "_content": "tna:DivisionReference=admd2", "author": "31575009@N05"}, {"raw": "tna:DepartmentReference=ADM", "machine_tag": 1, "id": "31569669-5033555370-108877269", "_content": "tna:DepartmentReference=adm", "author": "31575009@N05"}]}, "comments": {"_content": "0"}, "secret": "402f94d608", "usage": {"canblog": 0, "canshare": 1, "candownload": 1, "canprint": 0}, "description": {"_content": "<b>Description:</b> Page from the medical and surgical journal of A B Messer, Assistant Surgeon aboard HMS Curacoa. Plan of the interior of the gunboat sent from the ship to put down a Maori rebellion in New Zealand.\n\nThis assault is sometimes called the Waikato invasion and was the largest conflict between European migrants and the Maori in the mid-19th century New Zealand Wars.\n\n<b>Date:</b> 1863-4\n\n<b>Our Catalogue Reference:</b> <a href=\"http://www.nationalarchives.gov.uk/catalogue/displaycataloguedetails.asp?CATLN=7&amp;CATID=-6173792&amp;SearchInit=4&amp;SearchType=6&amp;CATREF=adm+101/239/2\" rel=\"nofollow\">ADM 101/239/2</a>\n\nThis image is from the collections of The National Archives. Feel free to share it within the spirit of the Commons.\n\nFor high quality reproductions of any item from our collection please contact our <a href=\"http://www.nationalarchives.gov.uk/imagelibrary\" rel=\"nofollow\">image library</a>."}, "isfavorite": 0, "views": "2335", "farm": 5, "visibility": {"isfriend": 0, "isfamily": 0, "ispublic": 1}, "rotation": 0, "dates": {"taken": "2010-09-16 12:31:14", "lastupdate": "1364411473", "takengranularity": "0", "posted": "1285687194"}, "originalsecret": "4a972cc157", "license": "7", "notes": {"note": []}, "server": "4129", "safety_level": "0", "urls": {"url": [{"type": "photopage", "_content": "http://www.flickr.com/photos/nationalarchives/5033555370/"}]}, "editability": {"canaddmeta": 0, "cancomment": 0}}, "stat": "ok"}