{"stat": "ok", "comments": {"comment": [{"permalink": "http://www.flickr.com/photos/library_of_congress/8009363571/#comment72157631631313180", "realname": "Art Siegel", "path_alias": "artolog", "author": "76016463@N00", "iconserver": "3807", "datecreate": "1348699259", "_content": "The American-Hawaiian Line steamer SS Nebraskan was torpedoed by the  Germans on May 27, 1915.  It was able to make it to port under its own power. \n\n<a href=\"http://trove.nla.gov.au/ndp/del/article/1520307?searchTerm=s.s.%20nebraskan&amp;searchLimits=sortby=dateAsc\" rel=\"nofollow\">trove.nla.gov.au/ndp/del/article/1520307?searchTerm=s.s.%...</a>", "authorname": "artolog", "id": "8602872-8009363571-72157631631313180", "iconfarm": 4}], "photo_id": "8009363571"}}