{"stat": "ok", "comments": {"comment": [{"permalink": "http://www.flickr.com/photos/lselibrary/7928643056/#comment72157634537736341", "realname": "Fierce Squish", "path_alias": null, "author": "98578332@N02", "iconserver": "7332", "datecreate": "1373266290", "_content": "nice  pic.", "authorname": "fiercesquish", "id": "35107159-7928643056-72157634537736341", "iconfarm": 8}, {"permalink": "http://www.flickr.com/photos/lselibrary/7928643056/#comment72157634705205220", "realname": "blot heels", "path_alias": null, "author": "99109812@N02", "iconserver": "0", "datecreate": "1374226769", "_content": "nice", "authorname": "blotheels", "id": "35107159-7928643056-72157634705205220", "iconfarm": 0}, {"permalink": "http://www.flickr.com/photos/lselibrary/7928643056/#comment72157635037649356", "realname": "Spring Splutter", "path_alias": null, "author": "100161388@N07", "iconserver": "7451", "datecreate": "1376286633", "_content": "good one", "authorname": "springsplutter", "id": "35107159-7928643056-72157635037649356", "iconfarm": 8}, {"permalink": "http://www.flickr.com/photos/lselibrary/7928643056/#comment72157635094357216", "realname": "Rose  Thompson", "path_alias": null, "author": "100400002@N08", "iconserver": "2889", "datecreate": "1376632787", "_content": "very nice", "authorname": "pantssleep", "id": "35107159-7928643056-72157635094357216", "iconfarm": 3}, {"permalink": "http://www.flickr.com/photos/lselibrary/7928643056/#comment72157635332169676", "realname": "litter tear", "path_alias": null, "author": "101032777@N03", "iconserver": "3788", "datecreate": "1378046367", "_content": "Excellent", "authorname": "littertear", "id": "35107159-7928643056-72157635332169676", "iconfarm": 4}, {"permalink": "http://www.flickr.com/photos/lselibrary/7928643056/#comment72157635353085249", "realname": "hoops mumpsimus", "path_alias": null, "author": "101230292@N06", "iconserver": "2825", "datecreate": "1378185379", "_content": "nice", "authorname": "hoopsmumpsimus", "id": "35107159-7928643056-72157635353085249", "iconfarm": 3}, {"permalink": "http://www.flickr.com/photos/lselibrary/7928643056/#comment72157635359857799", "realname": "Wes Zemel", "path_alias": null, "author": "101209139@N07", "iconserver": "7296", "datecreate": "1378223474", "_content": "excellent", "authorname": "WesZemel", "id": "35107159-7928643056-72157635359857799", "iconfarm": 8}, {"permalink": "http://www.flickr.com/photos/lselibrary/7928643056/#comment72157635398795509", "realname": "chocolate burgoo", "path_alias": null, "author": "101364198@N03", "iconserver": "3684", "datecreate": "1378454641", "_content": "amazing", "authorname": "chocolateburgoo", "id": "35107159-7928643056-72157635398795509", "iconfarm": 4}, {"permalink": "http://www.flickr.com/photos/lselibrary/7928643056/#comment72157635450108276", "realname": "nide toes", "path_alias": null, "author": "101479711@N02", "iconserver": "3756", "datecreate": "1378710828", "_content": "amazing", "authorname": "nidetoes", "id": "35107159-7928643056-72157635450108276", "iconfarm": 4}, {"permalink": "http://www.flickr.com/photos/lselibrary/7928643056/#comment72157635493510950", "realname": "Mariska Botha", "path_alias": null, "author": "101657531@N06", "iconserver": "5497", "datecreate": "1378974870", "_content": "Oh wow, very interesting...", "authorname": "mariskabotha56", "id": "35107159-7928643056-72157635493510950", "iconfarm": 6}, {"permalink": "http://www.flickr.com/photos/lselibrary/7928643056/#comment72157635555025652", "realname": "Rachel Manning", "path_alias": null, "author": "101906101@N04", "iconserver": "3797", "datecreate": "1379313970", "_content": "Amazing image.", "authorname": "rachelmanning784", "id": "35107159-7928643056-72157635555025652", "iconfarm": 4}, {"permalink": "http://www.flickr.com/photos/lselibrary/7928643056/#comment72157635935381623", "realname": "BinaryOptions Guru", "path_alias": null, "author": "103383574@N05", "iconserver": "7341", "datecreate": "1380256779", "_content": "Excellent...!!", "authorname": "BinaryOptionsGuru", "id": "35107159-7928643056-72157635935381623", "iconfarm": 8}, {"permalink": "http://www.flickr.com/photos/lselibrary/7928643056/#comment72157636282198923", "realname": "Mike Lewis", "path_alias": null, "author": "104508383@N07", "iconserver": "7362", "datecreate": "1381140247", "_content": "excellent", "authorname": "fartyankle", "id": "35107159-7928643056-72157636282198923", "iconfarm": 8}, {"permalink": "http://www.flickr.com/photos/lselibrary/7928643056/#comment72157636345959293", "realname": "scarlet runner", "path_alias": null, "author": "104727891@N02", "iconserver": "7344", "datecreate": "1381303292", "_content": "Its splendid :)", "authorname": "runnerscarlet", "id": "35107159-7928643056-72157636345959293", "iconfarm": 8}, {"permalink": "http://www.flickr.com/photos/lselibrary/7928643056/#comment72157636892812966", "realname": "Robert Daigneault", "path_alias": null, "author": "106437484@N05", "iconserver": "5526", "datecreate": "1382597517", "_content": "Its remarkable :)", "authorname": "robertdaigneault846", "id": "35107159-7928643056-72157636892812966", "iconfarm": 6}, {"permalink": "http://www.flickr.com/photos/lselibrary/7928643056/#comment72157637145547513", "realname": "Doris Burt", "path_alias": null, "author": "107179843@N07", "iconserver": "5488", "datecreate": "1383194495", "_content": "Oh wow, very interesting...", "authorname": "dorisburt622", "id": "35107159-7928643056-72157637145547513", "iconfarm": 6}, {"permalink": "http://www.flickr.com/photos/lselibrary/7928643056/#comment72157637405323645", "realname": "Elaine Flannagan", "path_alias": null, "author": "107936532@N04", "iconserver": "5517", "datecreate": "1383816618", "_content": "Its splendid :)", "authorname": "flannaganelaine", "id": "35107159-7928643056-72157637405323645", "iconfarm": 6}, {"permalink": "http://www.flickr.com/photos/lselibrary/7928643056/#comment72157637618081315", "realname": "compar esheds", "path_alias": null, "author": "108550194@N02", "iconserver": "3767", "datecreate": "1384317201", "_content": "Its incredible :)", "authorname": "comparesheds1", "id": "35107159-7928643056-72157637618081315", "iconfarm": 4}, {"permalink": "http://www.flickr.com/photos/lselibrary/7928643056/#comment72157638567537504", "realname": "furbelow wrong", "path_alias": null, "author": "111186244@N07", "iconserver": "7370", "datecreate": "1386735102", "_content": "Its amazing", "authorname": "furbelowwrong", "id": "35107159-7928643056-72157638567537504", "iconfarm": 8}, {"permalink": "http://www.flickr.com/photos/lselibrary/7928643056/#comment72157638655139584", "realname": "tears blush", "path_alias": null, "author": "111455624@N07", "iconserver": "5502", "datecreate": "1386999451", "_content": "Its interesting :)", "authorname": "tearsblush", "id": "35107159-7928643056-72157638655139584", "iconfarm": 6}, {"permalink": "http://www.flickr.com/photos/lselibrary/7928643056/#comment72157638815520935", "realname": "belts lime", "path_alias": null, "author": "111903235@N05", "iconserver": "0", "datecreate": "1387434060", "_content": "terrific", "authorname": "beltslime", "id": "35107159-7928643056-72157638815520935", "iconfarm": 0}, {"permalink": "http://www.flickr.com/photos/lselibrary/7928643056/#comment72157638816999466", "realname": "ritzy hat", "path_alias": null, "author": "111939054@N02", "iconserver": "3732", "datecreate": "1387444066", "_content": "amazing", "authorname": "ritzyhat", "id": "35107159-7928643056-72157638816999466", "iconfarm": 4}, {"permalink": "http://www.flickr.com/photos/lselibrary/7928643056/#comment72157638818414415", "realname": "Harmony Home", "path_alias": null, "author": "111928622@N04", "iconserver": "5495", "datecreate": "1387444538", "_content": "Interesting...!!", "authorname": "harmony_home1", "id": "35107159-7928643056-72157638818414415", "iconfarm": 6}], "photo_id": "7928643056"}}