{"stat": "ok", "comments": {"comment": [{"permalink": "http://www.flickr.com/photos/library_of_congress/5269523976/#comment72157625495221767", "realname": "", "path_alias": null, "author": "23103743@N05", "iconserver": "2155", "datecreate": "1292641223", "_content": "<a href=\"http://en.wikipedia.org/wiki/Cliff_Edwards\" rel=\"nofollow\">en.wikipedia.org/wiki/Cliff_Edwards</a>\nAlso, see <a href=\"http://effyeahcliffedwards.tumblr.com/\" rel=\"nofollow\">effyeahcliffedwards.tumblr.com/</a>", "authorname": "swanq", "id": "8602872-5269523976-72157625495221767", "iconfarm": 3}, {"permalink": "http://www.flickr.com/photos/library_of_congress/5269523976/#comment72157625621046522", "realname": "", "path_alias": null, "author": "23103743@N05", "iconserver": "2155", "datecreate": "1292642698", "_content": "Dumor PLastics made plastic for records.  See\n  <a href=\"http://books.google.com/books?id=qwwEAAAAMBAJ&amp;pg=PT33&amp;lpg=PT33\" rel=\"nofollow\">books.google.com/books?id=qwwEAAAAMBAJ&amp;pg=PT33&amp;lp...</a>", "authorname": "swanq", "id": "8602872-5269523976-72157625621046522", "iconfarm": 3}], "photo_id": "5269523976"}}