{"photo": {"people": {"haspeople": 0}, "dateuploaded": "1334350433", "originalformat": "jpg", "owner": {"username": "San Diego Air & Space Museum Archives", "realname": "SDASM Archives", "nsid": "49487266@N07", "iconserver": "4070", "location": "", "path_alias": "sdasmarchives", "iconfarm": 5}, "publiceditability": {"canaddmeta": 1, "cancomment": 1}, "id": "7074703591", "title": {"_content": "E-1B, NE-787 1"}, "media": "photo", "tags": {"tag": []}, "comments": {"_content": "0"}, "secret": "4df7934318", "usage": {"canblog": 0, "canshare": 1, "candownload": 1, "canprint": 0}, "description": {"_content": "From a collection of 16mm slides showing the US Navy and Gliding at Torrey Pines, from an unknown donor. \n\nRepository : <a href=\"http://www.sandiegoairandspace.org/library/stillimages.html\" rel=\"nofollow\">San Diego Air and Space Museum Archive</a>"}, "isfavorite": 0, "views": "441", "farm": 6, "visibility": {"isfriend": 0, "isfamily": 0, "ispublic": 1}, "rotation": 0, "dates": {"taken": "2012-04-06 16:46:36", "lastupdate": "1334756873", "takengranularity": "0", "posted": "1334350433"}, "originalsecret": "b35a18a686", "license": "7", "notes": {"note": []}, "server": "5118", "safety_level": "0", "urls": {"url": [{"type": "photopage", "_content": "http://www.flickr.com/photos/sdasmarchives/7074703591/"}]}, "editability": {"canaddmeta": 0, "cancomment": 0}}, "stat": "ok", "flarchive:created": 1387758552}