{"photo": {"people": {"haspeople": 0}, "dateuploaded": "1199392099", "originalformat": "jpg", "owner": {"username": "The Library of Congress", "realname": "", "nsid": "8623220@N02", "iconserver": "3703", "location": "", "path_alias": "library_of_congress", "iconfarm": 4}, "publiceditability": {"canaddmeta": 1, "cancomment": 1}, "id": "2163917904", "title": {"_content": "Mrs. Field  (LOC)"}, "media": "photo", "tags": {"tag": [{"raw": "Library of Congress", "machine_tag": false, "id": "8602872-2163917904-22301", "_content": "libraryofcongress", "author": "8623220@N02"}, {"raw": "dc:identifier=http://hdl.loc.gov/loc.pnp/ggbain.10486", "machine_tag": 1, "id": "8602872-2163917904-18916970", "_content": "dc:identifier=httphdllocgovlocpnpggbain10486", "author": "8623220@N02"}, {"raw": "xmlns:dc=http://purl.org/dc/elements/1.1/", "machine_tag": true, "id": "8602872-2163917904-8499312", "_content": "xmlns:dc=httppurlorgdcelements11", "author": "8623220@N02"}, {"raw": "georgegranthambaincollection", "machine_tag": false, "id": "8602872-2163917904-3373323", "_content": "georgegranthambaincollection", "author": "64105875@N00"}, {"raw": "LOC", "machine_tag": false, "id": "8602872-2163917904-22299", "_content": "loc", "author": "64105875@N00"}, {"raw": "woman", "machine_tag": false, "id": "8602872-2163917904-347", "_content": "woman", "author": "64105875@N00"}, {"raw": "man", "machine_tag": false, "id": "8602872-2163917904-466", "_content": "man", "author": "64105875@N00"}, {"raw": "black", "machine_tag": false, "id": "8602872-2163917904-472", "_content": "black", "author": "64105875@N00"}, {"raw": "white", "machine_tag": false, "id": "8602872-2163917904-395", "_content": "white", "author": "64105875@N00"}, {"raw": "whitewoman", "machine_tag": 0, "id": "8602872-2163917904-911120", "_content": "whitewoman", "author": "64105875@N00"}, {"raw": "blackman", "machine_tag": 0, "id": "8602872-2163917904-28149", "_content": "blackman", "author": "64105875@N00"}, {"raw": "1900s", "machine_tag": false, "id": "8602872-2163917904-121048", "_content": "1900s", "author": "64105875@N00"}, {"raw": "chair", "machine_tag": false, "id": "8602872-2163917904-2917", "_content": "chair", "author": "64105875@N00"}, {"raw": "wheelchair", "machine_tag": 0, "id": "8602872-2163917904-6248", "_content": "wheelchair", "author": "64105875@N00"}, {"raw": "rich", "machine_tag": 0, "id": "8602872-2163917904-6747", "_content": "rich", "author": "64105875@N00"}, {"raw": "wealthy", "machine_tag": 0, "id": "8602872-2163917904-25776", "_content": "wealthy", "author": "64105875@N00"}, {"raw": "fancy", "machine_tag": 0, "id": "8602872-2163917904-16357", "_content": "fancy", "author": "64105875@N00"}, {"raw": "servant", "machine_tag": 0, "id": "8602872-2163917904-115946", "_content": "servant", "author": "64105875@N00"}, {"raw": "mrs.field", "machine_tag": 0, "id": "8602872-2163917904-19373814", "_content": "mrsfield", "author": "64105875@N00"}, {"raw": "hats", "machine_tag": false, "id": "8602872-2163917904-7665", "_content": "hats", "author": "90689439@N00"}, {"raw": "wicker", "machine_tag": 0, "id": "8602872-2163917904-35479", "_content": "wicker", "author": "90689439@N00"}, {"raw": "derby", "machine_tag": 0, "id": "8602872-2163917904-51355", "_content": "derby", "author": "76016463@N00"}, {"raw": "field", "machine_tag": false, "id": "8602872-2163917904-915", "_content": "field", "author": "76016463@N00"}, {"raw": "Bain News Service", "machine_tag": false, "id": "8602872-2163917904-19282603", "_content": "bainnewsservice", "author": "15965815@N00"}, {"raw": "glass negative", "machine_tag": false, "id": "8602872-2163917904-201865", "_content": "glassnegative", "author": "15965815@N00"}, {"raw": "Bain Collection", "machine_tag": false, "id": "8602872-2163917904-11507727", "_content": "baincollection", "author": "15965815@N00"}, {"raw": "black and white", "machine_tag": false, "id": "8602872-2163917904-293", "_content": "blackandwhite", "author": "15965815@N00"}, {"raw": "B&W", "machine_tag": false, "id": "8602872-2163917904-294", "_content": "bw", "author": "15965815@N00"}, {"raw": "umbrella", "machine_tag": false, "id": "8602872-2163917904-1340", "_content": "umbrella", "author": "23212881@N06"}, {"raw": "fur", "machine_tag": 0, "id": "8602872-2163917904-1648", "_content": "fur", "author": "23212881@N06"}, {"raw": "veiled", "machine_tag": 0, "id": "8602872-2163917904-3849", "_content": "veiled", "author": "23212881@N06"}]}, "comments": {"_content": "5"}, "secret": "6d206ff68c", "usage": {"canblog": 0, "canshare": 1, "candownload": 1, "canprint": 0}, "description": {"_content": "Bain News Service,, publisher.\n\nMrs. Field\n\n[between ca. 1910 and ca. 1915]\n\n1 negative : glass ; 5 x 7 in. or smaller.\n\n<b>Notes:\n</b> Title from unverified data provided by the Bain News Service on the negatives or caption cards.\nForms part of: George Grantham Bain Collection (Library of Congress).\n\n<b>Format: </b> Glass negatives.\n\n<b>Rights Info: </b> No known restrictions on publication.\n\n<b>Repository: </b> Library of Congress, Prints and Photographs Division, Washington, D.C. 20540 USA, <a href=\"http://hdl.loc.gov/loc.pnp/pp.print\" rel=\"nofollow\">hdl.loc.gov/loc.pnp/pp.print</a>\n\nGeneral information about the Bain Collection is available at <a href=\"http://hdl.loc.gov/loc.pnp/pp.ggbain\" rel=\"nofollow\">hdl.loc.gov/loc.pnp/pp.ggbain</a>\n\n<b>Higher resolution image is available (Persistent URL): </b>  <a href=\"http://hdl.loc.gov/loc.pnp/ggbain.10486\" rel=\"nofollow\">hdl.loc.gov/loc.pnp/ggbain.10486</a>\n\n<b>Call Number: </b> LC-B2- 2409-15\n\n"}, "isfavorite": 0, "views": "3863", "farm": 3, "visibility": {"isfriend": 0, "isfamily": 0, "ispublic": 1}, "rotation": 0, "dates": {"taken": "1910-01-01 00:00:00", "lastupdate": "1362770147", "takengranularity": "8", "posted": "1199392099"}, "originalsecret": "4fcff2fb5f", "license": "7", "notes": {"note": []}, "server": "2133", "safety_level": "0", "urls": {"url": [{"type": "photopage", "_content": "http://www.flickr.com/photos/library_of_congress/2163917904/"}]}, "editability": {"canaddmeta": 0, "cancomment": 0}}, "stat": "ok"}