{"stat": "ok", "comments": {"comment": [{"permalink": "http://www.flickr.com/photos/library_of_congress/3449511917/#comment72157616949718782", "realname": "", "path_alias": null, "author": "23138766@N03", "iconserver": "3349", "datecreate": "1239996581", "_content": "this is a great shot, my friend!", "authorname": "memkee", "id": "8602872-3449511917-72157616949718782", "iconfarm": 4}, {"permalink": "http://www.flickr.com/photos/library_of_congress/3449511917/#comment72157616860610407", "realname": "", "path_alias": "kamoteus", "author": "21295125@N05", "iconserver": "2399", "datecreate": "1239997532", "_content": "utstanding!\n\nneed to visit this place one day!", "authorname": "Kamoteus (A New Beginning)", "id": "8602872-3449511917-72157616860610407", "iconfarm": 3}, {"permalink": "http://www.flickr.com/photos/library_of_congress/3449511917/#comment72157616860630203", "realname": "", "path_alias": "kamoteus", "author": "21295125@N05", "iconserver": "2399", "datecreate": "1239997542", "_content": "Hi, I'm an admin for a group called <a href=\"http://www.flickr.com/groups/747737@N24/\">*****Through Your Eyes***** (Invites Only)</a>, and we'd love to have this added to the group!", "authorname": "Kamoteus (A New Beginning)", "id": "8602872-3449511917-72157616860630203", "iconfarm": 3}, {"permalink": "http://www.flickr.com/photos/library_of_congress/3449511917/#comment72157616863628449", "realname": "Ian Howie", "path_alias": "ianhowie", "author": "36221782@N00", "iconserver": "51", "datecreate": "1240001425", "_content": "Great shot. I was born and raised in Mauchline and used to spend a lot of time on the river around the viaduct. We used to walk to school in Auchinleck and dare each other to cross the bridge when it was still a busy rail line. \n\nGreat to see it again.", "authorname": "Ian Howie", "id": "8602872-3449511917-72157616863628449", "iconfarm": 1}, {"permalink": "http://www.flickr.com/photos/library_of_congress/3449511917/#comment72157616864207189", "realname": "Ian Livesey", "path_alias": "ianlivesey", "author": "29488979@N06", "iconserver": "3014", "datecreate": "1240002550", "_content": "Hi, I'm an admin for a group called <a href=\"http://www.flickr.com/groups/1031490@N25/\">The UK Photographer</a>, and we'd love to have this added to the group!\n\nLove to have you join the group.", "authorname": "Ian Livesey", "id": "8602872-3449511917-72157616864207189", "iconfarm": 4}, {"permalink": "http://www.flickr.com/photos/library_of_congress/3449511917/#comment72157616973633866", "realname": "", "path_alias": "amtfoto", "author": "14753713@N08", "iconserver": "0", "datecreate": "1240049692", "_content": "Is this real, \naaaaahhhhhhhhh", "authorname": "am\u2020\u0192o\u2020o", "id": "8602872-3449511917-72157616973633866", "iconfarm": 0}, {"permalink": "http://www.flickr.com/photos/library_of_congress/3449511917/#comment72157616929115455", "realname": "Gavin Veasey", "path_alias": "gavinovz", "author": "29619972@N00", "iconserver": "7413", "datecreate": "1240106609", "_content": "I can't believe how old this is!", "authorname": "gavinvz", "id": "8602872-3449511917-72157616929115455", "iconfarm": 8}, {"permalink": "http://www.flickr.com/photos/library_of_congress/3449511917/#comment72157625873022958", "realname": "Gordon Thomson", "path_alias": "killie65", "author": "11928221@N04", "iconserver": "1121", "datecreate": "1295607407", "_content": "This magnificent viaduct carries the Glasgow &amp; South Western railway's main line from Carlisle to Glasgow via Dumfries &amp; Kilmarnock over the River Ayr, just south of Mauchline, Ayrshire.\nThis viaduct was built 1846 - 1848 using locally quarried sandstone. The railway was opened on 20-05-1850 and remains open today for both freight and passenger traffic.\nThe central span was the largest span of a masonry arch in the world when built (181 feet, 55 metres) and is the largest in the U.K. The crown of the arch is 175 feet, 54 metres above the River bed.", "authorname": "agcthoms", "id": "8602872-3449511917-72157625873022958", "iconfarm": 2}], "photo_id": "3449511917"}}