{"photo": {"people": {"haspeople": 0}, "dateuploaded": "1233014591", "originalformat": "jpg", "owner": {"username": "National Library NZ on The Commons", "realname": "", "nsid": "32741315@N06", "iconserver": "3285", "location": "Wellington, New Zealand", "path_alias": "nationallibrarynz_commons", "iconfarm": 4}, "publiceditability": {"canaddmeta": 1, "cancomment": 1}, "id": "3230175060", "title": {"_content": "Business centre, Cambridge, 1924"}, "media": "photo", "tags": {"tag": [{"raw": "nationallibrarynz", "machine_tag": 0, "id": "32695993-3230175060-31988483", "_content": "nationallibrarynz", "author": "32741315@N06"}, {"raw": "cityscape", "machine_tag": 0, "id": "32695993-3230175060-3643", "_content": "cityscape", "author": "34427466731@N01"}, {"raw": "panorama", "machine_tag": 0, "id": "32695993-3230175060-306", "_content": "panorama", "author": "34427466731@N01"}, {"raw": "panoramic", "machine_tag": 0, "id": "32695993-3230175060-9696", "_content": "panoramic", "author": "34427466731@N01"}, {"raw": "streets", "machine_tag": 0, "id": "32695993-3230175060-505", "_content": "streets", "author": "34427466731@N01"}, {"raw": "buildings", "machine_tag": 0, "id": "32695993-3230175060-1399", "_content": "buildings", "author": "34427466731@N01"}, {"raw": "business centre", "machine_tag": 0, "id": "32695993-3230175060-1629386", "_content": "businesscentre", "author": "34427466731@N01"}, {"raw": "Cambridge", "machine_tag": 0, "id": "32695993-3230175060-211", "_content": "cambridge", "author": "34427466731@N01"}, {"raw": "1924", "machine_tag": 0, "id": "32695993-3230175060-142445", "_content": "1924", "author": "61489055@N00"}]}, "comments": {"_content": "2"}, "geoperms": {"isfriend": 0, "isfamily": 0, "ispublic": 1, "iscontact": 0}, "secret": "1689946372", "location": {"locality": {"woeid": "2348268", "place_id": "vvH7pglTUb6kHxkX", "_content": "Cambridge"}, "country": {"woeid": "23424916", "place_id": "X_2zAGVTUb5..jhXDw", "_content": "New Zealand"}, "region": {"woeid": "15021765", "place_id": "CR3kkzZQV7rix55kVg", "_content": "Waikato"}, "place_id": "jMUks8BTWrw.Q999uw", "longitude": 175.470006, "county": {"woeid": "55875913", "place_id": "w8SaerdUV7IvxyoYmQ", "_content": "Waipa District"}, "context": "0", "woeid": "28676723", "latitude": -37.894837, "neighbourhood": {"woeid": "28676723", "place_id": "jMUks8BTWrw.Q999uw", "_content": "Cambridge Central"}, "accuracy": "16"}, "usage": {"canblog": 0, "canshare": 1, "candownload": 1, "canprint": 0}, "description": {"_content": "Photographer: Robert Percy Moore\nBusiness centre, Cambridge, 1924\nSilver gelatin photoprint\nReference number: PA6-002\nPhotographic Archive, Alexander Turnbull Library, National Library of New Zealand\n\n<a href=\"http://natlib.govt.nz/records/22591161\" rel=\"nofollow\">Find out more about this image</a> from the <a href=\"http://natlib.govt.nz\" rel=\"nofollow\">Alexander Turnbull Library.</a>"}, "isfavorite": 0, "views": "3623", "farm": 4, "visibility": {"isfriend": 0, "isfamily": 0, "ispublic": 1}, "rotation": 0, "dates": {"taken": "1924-01-01 00:00:00", "lastupdate": "1375841543", "takengranularity": "6", "posted": "1233014591"}, "originalsecret": "938621a28a", "license": "7", "notes": {"note": []}, "server": "3264", "safety_level": "0", "urls": {"url": [{"type": "photopage", "_content": "http://www.flickr.com/photos/nationallibrarynz_commons/3230175060/"}]}, "editability": {"canaddmeta": 0, "cancomment": 0}}, "stat": "ok"}