{"photo": {"people": {"haspeople": 0}, "dateuploaded": "1319784099", "originalformat": "jpg", "owner": {"username": "National Library of Norway", "realname": "Nasjonalbiblioteket", "nsid": "48220291@N04", "iconserver": "4072", "location": "Norway", "path_alias": "national_library_of_norway", "iconfarm": 5}, "publiceditability": {"canaddmeta": 1, "cancomment": 1}, "id": "6288329912", "title": {"_content": "Portrett av Gina Krog"}, "media": "photo", "tags": {"tag": [{"raw": "Nasjonalbiblioteket", "machine_tag": 0, "id": "48188152-6288329912-4937297", "_content": "nasjonalbiblioteket", "author": "48220291@N04"}, {"raw": "National Library of Norway", "machine_tag": 0, "id": "48188152-6288329912-53595536", "_content": "nationallibraryofnorway", "author": "48220291@N04"}, {"raw": "portretter", "machine_tag": 0, "id": "48188152-6288329912-885237", "_content": "portretter", "author": "48220291@N04"}, {"raw": "kvinner", "machine_tag": 0, "id": "48188152-6288329912-1539364", "_content": "kvinner", "author": "48220291@N04"}, {"raw": "kvinnesak", "machine_tag": 0, "id": "48188152-6288329912-36935154", "_content": "kvinnesak", "author": "48220291@N04"}, {"raw": "visittkort", "machine_tag": 0, "id": "48188152-6288329912-1270699", "_content": "visittkort", "author": "48220291@N04"}, {"raw": "Gina Krog", "machine_tag": 0, "id": "48188152-6288329912-77278103", "_content": "ginakrog", "author": "48220291@N04"}, {"raw": "kvinnesaksforkjempere", "machine_tag": 0, "id": "48188152-6288329912-77279039", "_content": "kvinnesaksforkjempere", "author": "48220291@N04"}]}, "comments": {"_content": "0"}, "secret": "94d56ea3f7", "usage": {"canblog": 0, "canshare": 1, "candownload": 1, "canprint": 0}, "description": {"_content": "<b>Tittel / Title:</b> Portrett av Gina Krog\n<b>Motiv / Motif:</b> Visittkort.\n<b>Dato / Date:</b> ukjent / unknown\n<b>Fotograf / Photographer:</b> <a href=\"http://www.nb.no/nmff/fotograf.php?fotograf_id=1263&amp;navn=klem&amp;m_saml=&amp;kjonn=&amp;stikkord=&amp;year_from=&amp;year_to=&amp;stedsnavn=&amp;country_code=&amp;fylke_code=&amp;startid=0\" rel=\"nofollow\">Frederik Klem (1823-1895)</a>\n<b>Sted / Place:</b> Oslo\n<b>Eier / Owner Institution:</b> Nasjonalbiblioteket / National Library of Norway\n<b>Lenke / Link:</b> <a href=\"http://www.nb.no\" rel=\"nofollow\">www.nb.no</a>\n<b>Bildesignatur / Image Number:</b> blds_04507"}, "isfavorite": 0, "views": "728", "farm": 7, "visibility": {"isfriend": 0, "isfamily": 0, "ispublic": 1}, "rotation": 0, "dates": {"taken": "2011-10-24 08:54:45", "lastupdate": "1381958361", "takengranularity": "0", "posted": "1319784099"}, "originalsecret": "6f71571e73", "license": "7", "notes": {"note": []}, "server": "6032", "safety_level": "0", "urls": {"url": [{"type": "photopage", "_content": "http://www.flickr.com/photos/national_library_of_norway/6288329912/"}]}, "editability": {"canaddmeta": 0, "cancomment": 0}}, "stat": "ok"}