{"stat": "ok", "comments": {"comment": [{"permalink": "http://www.flickr.com/photos/powerhouse_museum/4773153377/#comment72157624404128937", "realname": "", "path_alias": "6lell9", "author": "29107395@N07", "iconserver": "6105", "datecreate": "1279473102", "_content": "This is fabulous! What a pity they don`t make places like this any more...", "authorname": "6lell9", "id": "24762863-4773153377-72157624404128937", "iconfarm": 7}, {"permalink": "http://www.flickr.com/photos/powerhouse_museum/4773153377/#comment72157624584591371", "realname": "Thierry Vrakking", "path_alias": "voetweekwater", "author": "27783275@N07", "iconserver": "5522", "datecreate": "1281617691", "_content": "i totally agree with 6Lell9", "authorname": "eighty eight televisions", "id": "24762863-4773153377-72157624584591371", "iconfarm": 6}], "photo_id": "4773153377"}}