{"stat": "ok", "comments": {"comment": [{"permalink": "http://www.flickr.com/photos/library_of_congress/2889445001/#comment72157607525486064", "realname": "", "path_alias": null, "author": "23103743@N05", "iconserver": "2155", "datecreate": "1222480550", "_content": "See <a href=\"http://www.flickr.com/photos/library_of_congress/2890280748/\">www.flickr.com/photos/library_of_congress/2890280748/</a> wrtt John L. Stevens.\n\nCould this woman be an older version of Rowena Edson Stevens as at <a href=\"http://celebratesuffrage2008.org/History.php\">celebratesuffrage2008.org/History.php</a> ?  Or as at <a href=\"http://www.ames.lib.ia.us/farwell/publication/Pub2199.htm\">www.ames.lib.ia.us/farwell/publication/Pub2199.htm</a> ?  If so, that would confirm this as being Judge John Loomis Stevens of Iowa.", "authorname": "swanq", "id": "8602872-2889445001-72157607525486064", "iconfarm": 3}, {"permalink": "http://www.flickr.com/photos/library_of_congress/2889445001/#comment72157608395568407", "realname": "", "path_alias": null, "author": "31821737@N06", "iconserver": "0", "datecreate": "1225053840", "_content": "This is Judge John Loomis Stevens and his wife Rowena Edson Stevens.  They were my great great grandparents.  He was a candidate for Governor of Iowa and this photo actually appeared in a 1912 publication regarding his candidacy.", "authorname": "carrierasmussen", "id": "8602872-2889445001-72157608395568407", "iconfarm": 0}], "photo_id": "2889445001"}}