{"photo": {"people": {"haspeople": 0}, "dateuploaded": "1273618190", "originalformat": "jpg", "owner": {"username": "National Library NZ on The Commons", "realname": "", "nsid": "32741315@N06", "iconserver": "3285", "location": "Wellington, New Zealand", "path_alias": "nationallibrarynz_commons", "iconfarm": 4}, "publiceditability": {"canaddmeta": 1, "cancomment": 1}, "id": "4599974860", "title": {"_content": "Princes Street, Auckland City, ca 1900"}, "media": "photo", "tags": {"tag": [{"raw": "nationallibrarynz", "machine_tag": 0, "id": "32695993-4599974860-31988483", "_content": "nationallibrarynz", "author": "32741315@N06"}, {"raw": "auckland", "machine_tag": 0, "id": "32695993-4599974860-12521", "_content": "auckland", "author": "69005233@N00"}, {"raw": "new zealand", "machine_tag": 0, "id": "32695993-4599974860-232", "_content": "newzealand", "author": "69005233@N00"}, {"raw": "bicycle", "machine_tag": 0, "id": "32695993-4599974860-956", "_content": "bicycle", "author": "69005233@N00"}, {"raw": "tree", "machine_tag": 0, "id": "32695993-4599974860-556", "_content": "tree", "author": "69005233@N00"}, {"raw": "street", "machine_tag": 0, "id": "32695993-4599974860-85", "_content": "street", "author": "69005233@N00"}, {"raw": "cabbage tree", "machine_tag": 0, "id": "32695993-4599974860-40935", "_content": "cabbagetree", "author": "69005233@N00"}]}, "comments": {"_content": "0"}, "geoperms": {"isfriend": 0, "isfamily": 0, "ispublic": 1, "iscontact": 0}, "secret": "27dd83e50a", "location": {"locality": {"woeid": "2348079", "place_id": "hddaVVdTUb7tdABf", "_content": "Auckland"}, "country": {"woeid": "23424916", "place_id": "X_2zAGVTUb5..jhXDw", "_content": "New Zealand"}, "region": {"woeid": "15021756", "place_id": "XIVOdI5QV7pepC5JCA", "_content": "Auckland"}, "place_id": "Xt08wq1TWryYSHzVrg", "longitude": 174.768973, "county": {"woeid": "55875921", "place_id": "bRzwje9UV7I.CCmLYA", "_content": "Auckland City"}, "context": "0", "woeid": "28676717", "latitude": -36.850294, "neighbourhood": {"woeid": "28676717", "place_id": "Xt08wq1TWryYSHzVrg", "_content": "Auckland Central"}, "accuracy": "16"}, "usage": {"canblog": 0, "canshare": 1, "candownload": 1, "canprint": 0}, "description": {"_content": "Princes Street, Auckland City, ca 1900\nReference Number: 1/2-000875-G\nPhotographer: William Archer Price\nDry plate glass negative\nPrice Collection, Photographic Archive, Alexander Turnbull Library\n\n\n<a href=\"http://mp.natlib.govt.nz/detail/?id=11688\" rel=\"nofollow\">Find out more about this image on our Manuscripts + Pictorial website</a>"}, "isfavorite": 0, "views": "2005", "farm": 5, "visibility": {"isfriend": 0, "isfamily": 0, "ispublic": 1}, "rotation": 0, "dates": {"taken": "1900-00-01 00:00:00", "lastupdate": "1347480268", "takengranularity": "8", "posted": "1273618190"}, "originalsecret": "74f5b4444a", "license": "7", "notes": {"note": []}, "server": "4049", "safety_level": "0", "urls": {"url": [{"type": "photopage", "_content": "http://www.flickr.com/photos/nationallibrarynz_commons/4599974860/"}]}, "editability": {"canaddmeta": 0, "cancomment": 0}}, "stat": "ok"}