{"photo": {"people": {"haspeople": 0}, "dateuploaded": "1392129945", "originalformat": "jpg", "owner": {"username": "The British Library", "realname": "", "nsid": "12403504@N02", "iconserver": "7437", "location": "", "path_alias": "britishlibrary", "iconfarm": 8}, "publiceditability": {"canaddmeta": 1, "cancomment": 1}, "id": "12458855975", "title": {"_content": "A voyage to Hudson's-Bay, ... in ... 1746 and 1747 - caption: 'Several creatures'"}, "media": "photo", "tags": {"tag": [{"machine_tag": 0, "_content": "languageenglish", "author": "12403504@N02", "raw": "language:English", "authorname": "The British Library", "id": "12383156-12458855975-2638137"}, {"machine_tag": 0, "_content": "shelfmarkg16019", "author": "12403504@N02", "raw": "shelfmark:G.16019", "authorname": "The British Library", "id": "12383156-12458855975-190823195"}, {"machine_tag": 0, "_content": "blimagesonline", "author": "12403504@N02", "raw": "bl_imagesonline", "authorname": "The British Library", "id": "12383156-12458855975-190861784"}, {"machine_tag": 1, "_content": "text:caption=severalcreatures", "author": "12403504@N02", "raw": "text:caption=Several creatures", "authorname": "The British Library", "id": "12383156-12458855975-190823205"}, {"machine_tag": 1, "_content": "dc:language=english", "author": "12403504@N02", "raw": "dc:language=English", "authorname": "The British Library", "id": "12383156-12458855975-190864014"}, {"machine_tag": 1, "_content": "dc:title=avoyagetohudsonsbayin1746and1747", "author": "12403504@N02", "raw": "dc:title=A voyage to Hudson's-Bay, ... in ... 1746 and 1747", "authorname": "The British Library", "id": "12383156-12458855975-190823215"}]}, "comments": {"_content": "0"}, "secret": "6ffd804dc9", "usage": {"canblog": 0, "canshare": 1, "candownload": 1, "canprint": 0}, "description": {"_content": "<strong>ID:</strong> <a href=\"https://imagesonline.bl.uk/?service=search&amp;action=do_quick_search&amp;language=en&amp;q=068560\" rel=\"nofollow\">068560</a>\n\n<strong>Title: A voyage to Hudson's-Bay, ... in ... 1746 and 1747</strong>\n\n<strong>Provenance:</strong> \n  H. Whitridge: London, 1748\n\n<strong>Caption:</strong> Several creatures\n\n<strong>Notes:</strong> An illustration showing a sea unicorn; a whale; a sea horse; seal with a cawl; blackside seal and white bear.\nImage taken from A voyage to Hudson's-Bay, in 1746 and 1747, for discovering a North West Passage\nOriginally published/produced in H. Whitridge: London, 1748.\n\n<strong>Language:</strong> English\n\n<strong>Source identifier:</strong> G.16019, opposite 134\n\n<strong>British Library Shelfmark:</strong> G.16019\n\nIf you wish to purchase a high quality copy of this image, please place an order at Images Online <a href=\"http://imagesonline.bl.uk\" rel=\"nofollow\">imagesonline.bl.uk</a>. The details from the above list should help you locate the images."}, "isfavorite": 0, "views": "3048", "farm": 4, "visibility": {"isfriend": 0, "isfamily": 0, "ispublic": 1}, "rotation": 0, "dates": {"taken": "2014-02-11 14:45:45", "lastupdate": "1393423598", "takengranularity": "0", "posted": "1392129945"}, "originalsecret": "b320707ffe", "license": "7", "notes": {"note": []}, "server": "3739", "safety_level": "0", "urls": {"url": [{"type": "photopage", "_content": "http://www.flickr.com/photos/britishlibrary/12458855975/"}]}, "editability": {"canaddmeta": 0, "cancomment": 0}}, "stat": "ok", "flarchive:created": 1394315850}